{"title":"Modeling Change","markdown":{"headingText":"Modeling Change","containsRefs":false,"markdown":"\n```{r, echo=FALSE, results=\"hide\", warning=FALSE, message=FALSE}\n# Load packages\nlibrary(mosaic)\nlibrary(mosaicCore)\nlibrary(mosaicCalc)\n```\n\n## Rundown\n\n::: {.callout-note title=\"Learning goals\"}\n-   Recognize a differential equation.\n-   Test whether a given function is a solution to a given differential equation.\n-   Solve a simple differential equation of the form $\\frac{dy}{dx} = f(x)$ using antiderivatives.\n-   Explain why a differential equation has an infinite family of solutions.\n-   Use an initial condition to turn a general solution into the unique solution to the differential equation.\n-   Create a differential equation to model a written description of the rate of change.\n:::\n\n## Activities\n\n### Building Differential Equations\n\nEach scenario describes a system that changes over time. Write a differential equation that models the change.\n\n1.  A population $P$ grows at a rate proportional to the size of the population.\n2.  Dead leaves $L$ accumulate on the ground at a rate of 3 grams per square centimeter per year. At the same time, the leaves decompose at a continuous rate of 75% per year.\n3.  The principal $P$ of a home mortgage increases at a continuous rate of 5% a year and decreases by the annual payment of \\$10000.\n4.  Bacteria grow proportionally to the product of the current population $N$ and the difference between the carrying capacity $M$ and the current population $N$.\n\n### Solve the Differential Equation\n\nUse your knowledge of anti-derivatives to solve the following differential equations\n\n1.  $\\displaystyle{ \\frac{dy}{dx} = \\cos(2 \\pi x)}$\n2.  $\\displaystyle{ \\frac{ds}{dt} = a t + v}$ where $a$ and $v$ are constants.\n3.  $\\displaystyle{ \\frac{dP}{dq} = \\frac{100}{q}}$ where $P(1) = 200$.\n4.  $\\displaystyle{ \\frac{dy}{dx} = e^{-x}}$ where $P(2) = 0$.\n\n### Verifying Solutions to Differential Equations\n\nDetermine which of the following functions are solutions to the differential equation $$\n\\frac{dy}{dx} =3y.\n$$\n\n1.  $y=x^3$\n2.  $y=e^{3x}$\n3.  $y=\\sin(3x)+\\cos(3x)$\n4.  $y=0$\n\n\\\n\\\n\\\n\\\n\n## Solutions\n\n<details>\n\n<summary>Click for Solutions</summary>\n\n### Building Differential Equations\n\n1.  $\\frac{dP}{dt} = r P$\n2.  $\\frac{dL}{dt} = 3 - 0.75L$\n3.  $\\frac{dP}{dt} = 0.05P - 10000$\n4.  $\\frac{dP}{dt} = k N (M-N)$\n\n### Solve the Differential Equation\n\nUse your knowledge of anti-derivatives to solve the following differential equations\n\n1.  $\\displaystyle{ y = \\frac{1}{2\\pi} \\sin(2\\pi x) + C}$\n2.  $\\displaystyle{ s = \\frac{1}{2}a t^2 + vt + C}$\n3.  $\\displaystyle{ P = 100 \\ln (q) + 200}$\n4.  $\\displaystyle{ y = -e^{-x} + e^{-2}}$.\n\n### Verifying Solutions to Differential Equations\n\nWe must check whether $\\frac{dy}{dx} =3y.$\n\n1.  $\\frac{dy}{dx}=3x^2$ and $3y=3x^3$. These are not equal, so $y=x^3$ is NOT a solution.\n2.  $\\frac{dy}{dx}=3e^{3x}$ and $3y = 3e^{3x}$. These are equal, so $y=e^{3x}$ is a solution!\n3.  $\\frac{dy}{dx}=3\\cos(3x)-3\\sin(3x)$ and $3y=3\\sin(3x)+3\\cos(3x)$. These are not equal (they differ by a negative sign), so $y=\\sin(3x)+\\cos(3x)$ is NOT a solution.\n4.  $\\frac{dy}{dx}=0$ and $3y=0$. These are equal, so $y=0$ is a solution!\n\n</details>\n","srcMarkdownNoYaml":""},"formats":{"html":{"identifier":{"display-name":"HTML","target-format":"html","base-format":"html"},"execute":{"fig-width":7,"fig-height":5,"fig-format":"retina","fig-dpi":96,"df-print":"default","error":false,"eval":true,"cache":null,"freeze":false,"echo":true,"output":true,"warning":true,"include":true,"keep-md":false,"keep-ipynb":false,"ipynb":null,"enabled":null,"daemon":null,"daemon-restart":false,"debug":false,"ipynb-filters":[],"ipynb-shell-interactivity":null,"plotly-connected":true,"engine":"knitr"},"render":{"keep-tex":false,"keep-typ":false,"keep-source":false,"keep-hidden":false,"prefer-html":false,"output-divs":true,"output-ext":"html","fig-align":"default","fig-pos":null,"fig-env":null,"code-fold":"none","code-overflow":"scroll","code-link":false,"code-line-numbers":false,"code-tools":false,"tbl-colwidths":"auto","merge-includes":true,"inline-includes":false,"preserve-yaml":false,"latex-auto-mk":true,"latex-auto-install":true,"latex-clean":true,"latex-min-runs":1,"latex-max-runs":10,"latex-makeindex":"makeindex","latex-makeindex-opts":[],"latex-tlmgr-opts":[],"latex-input-paths":[],"latex-output-dir":null,"link-external-icon":false,"link-external-newwindow":false,"self-contained-math":false,"format-resources":[],"notebook-links":true},"pandoc":{"standalone":true,"wrap":"none","default-image-extension":"png","to":"html","output-file":"6A-DiffEq.html"},"language":{"toc-title-document":"Table of contents","toc-title-website":"On this page","related-formats-title":"Other Formats","related-notebooks-title":"Notebooks","source-notebooks-prefix":"Source","other-links-title":"Other Links","code-links-title":"Code Links","launch-dev-container-title":"Launch Dev Container","launch-binder-title":"Launch Binder","article-notebook-label":"Article Notebook","notebook-preview-download":"Download Notebook","notebook-preview-download-src":"Download Source","notebook-preview-back":"Back to Article","manuscript-meca-bundle":"MECA Bundle","section-title-abstract":"Abstract","section-title-appendices":"Appendices","section-title-footnotes":"Footnotes","section-title-references":"References","section-title-reuse":"Reuse","section-title-copyright":"Copyright","section-title-citation":"Citation","appendix-attribution-cite-as":"For attribution, please cite this work as:","appendix-attribution-bibtex":"BibTeX citation:","appendix-view-license":"View License","title-block-author-single":"Author","title-block-author-plural":"Authors","title-block-affiliation-single":"Affiliation","title-block-affiliation-plural":"Affiliations","title-block-published":"Published","title-block-modified":"Modified","title-block-keywords":"Keywords","callout-tip-title":"Tip","callout-note-title":"Note","callout-warning-title":"Warning","callout-important-title":"Important","callout-caution-title":"Caution","code-summary":"Code","code-tools-menu-caption":"Code","code-tools-show-all-code":"Show All Code","code-tools-hide-all-code":"Hide All Code","code-tools-view-source":"View Source","code-tools-source-code":"Source Code","tools-share":"Share","tools-download":"Download","code-line":"Line","code-lines":"Lines","copy-button-tooltip":"Copy to Clipboard","copy-button-tooltip-success":"Copied!","repo-action-links-edit":"Edit this page","repo-action-links-source":"View source","repo-action-links-issue":"Report an issue","back-to-top":"Back to top","search-no-results-text":"No results","search-matching-documents-text":"matching documents","search-copy-link-title":"Copy link to search","search-hide-matches-text":"Hide additional matches","search-more-match-text":"more match in this document","search-more-matches-text":"more matches in this document","search-clear-button-title":"Clear","search-text-placeholder":"","search-detached-cancel-button-title":"Cancel","search-submit-button-title":"Submit","search-label":"Search","toggle-section":"Toggle section","toggle-sidebar":"Toggle sidebar navigation","toggle-dark-mode":"Toggle dark mode","toggle-reader-mode":"Toggle reader mode","toggle-navigation":"Toggle navigation","crossref-fig-title":"Figure","crossref-tbl-title":"Table","crossref-lst-title":"Listing","crossref-thm-title":"Theorem","crossref-lem-title":"Lemma","crossref-cor-title":"Corollary","crossref-prp-title":"Proposition","crossref-cnj-title":"Conjecture","crossref-def-title":"Definition","crossref-exm-title":"Example","crossref-exr-title":"Exercise","crossref-ch-prefix":"Chapter","crossref-apx-prefix":"Appendix","crossref-sec-prefix":"Section","crossref-eq-prefix":"Equation","crossref-lof-title":"List of Figures","crossref-lot-title":"List of Tables","crossref-lol-title":"List of Listings","environment-proof-title":"Proof","environment-remark-title":"Remark","environment-solution-title":"Solution","listing-page-order-by":"Order By","listing-page-order-by-default":"Default","listing-page-order-by-date-asc":"Oldest","listing-page-order-by-date-desc":"Newest","listing-page-order-by-number-desc":"High to Low","listing-page-order-by-number-asc":"Low to High","listing-page-field-date":"Date","listing-page-field-title":"Title","listing-page-field-description":"Description","listing-page-field-author":"Author","listing-page-field-filename":"File Name","listing-page-field-filemodified":"Modified","listing-page-field-subtitle":"Subtitle","listing-page-field-readingtime":"Reading Time","listing-page-field-wordcount":"Word Count","listing-page-field-categories":"Categories","listing-page-minutes-compact":"{0} min","listing-page-category-all":"All","listing-page-no-matches":"No matching items","listing-page-words":"{0} words","listing-page-filter":"Filter","draft":"Draft"},"metadata":{"lang":"en","fig-responsive":true,"quarto-version":"1.5.57","editor":"visual","theme":"united","code-copy":true,"grid":{"sidebar-width":"200px","body-width":"1000px","margin-width":"150px"}},"extensions":{"book":{"multiFile":true}}}},"projectFormats":["html"]}